Metadata-Version: 2.2
Name: pyevil
Version: 0.0.9
Summary: EVIL PYTHON VOODOO
Author-email: Adam Jenca <jenca.adam@gmail.com>
Maintainer-email: Adam Jenca <jenca.adam@gmail.com>
License: MIT License
Project-URL: Homepage, https://github.com/jenca-adam/pyevil
Project-URL: Bug Reports, https://github.com/jenca-adam/pyevil/issues
Project-URL: Source, https://github.com/jenca-adam/pyevil
Keywords: c,evil,voodoo,unsafe
Classifier: Development Status :: 3 - Alpha
Classifier: Programming Language :: C
Classifier: Programming Language :: Python :: 3 :: Only
Classifier: Topic :: Software Development :: Libraries :: Python Modules
Classifier: Intended Audience :: Developers
License-File: LICENSE
